micsv/__init__.py
micsv/__main__.py
micsv/download.py
micsv/get_dowload_links.py
micsv/meta.py
micsv/run.py
micsv/run_mics.py
micsv-0.0.2.dist-info/LICENSE
micsv-0.0.2.dist-info/METADATA
micsv-0.0.2.dist-info/WHEEL
micsv-0.0.2.dist-info/top_level.txt
micsv-0.0.2.dist-info/RECORD
