Metadata-Version: 2.1
Name: micsv
Version: 0.0.2
Summary: Automate MICS survey downloading
Home-page: https://github.com/kklot/mics
Author: Kinh Nguyen
Author-email: van-kinh.nguyen@outlook.com
License: UNKNOWN
Platform: UNKNOWN
Classifier: Programming Language :: Python :: 3
Classifier: License :: OSI Approved :: MIT License
Classifier: Operating System :: OS Independent
Requires-Python: >=3.6
